editorjs/__about__.py
editorjs/__init__.py
editorjs/blocks.py
editorjs/core.py
editorjs/exceptions.py
editorjs/helpers.py
editorjs/types.py
edwh_editorjs-2.5.0.dist-info/METADATA
edwh_editorjs-2.5.0.dist-info/WHEEL
edwh_editorjs-2.5.0.dist-info/RECORD
