Metadata-Version: 2.3
Name: edwh-editorjs
Version: 2.5.0
Summary: EditorJS.py
Project-URL: Homepage, https://github.com/educationwarehouse/edwh-EditorJS
Author-email: SKevo <skevo.cw@gmail.com>, Robin van der Noord <robin.vdn@educationwarehouse.nl>
Keywords: bleach,clean,editor,editor.js,html,javascript,json,parser,wysiwyg
Classifier: Development Status :: 4 - Beta
Classifier: Intended Audience :: Developers
Classifier: License :: OSI Approved :: MIT License
Classifier: Programming Language :: Python :: 3.10
Classifier: Programming Language :: Python :: 3.11
Classifier: Programming Language :: Python :: 3.12
Classifier: Programming Language :: Python :: 3.13
Requires-Python: >=3.10
Requires-Dist: html2markdown
Requires-Dist: humanize
Requires-Dist: markdown2
Requires-Dist: mdast
Provides-Extra: dev
Requires-Dist: edwh; extra == 'dev'
Requires-Dist: hatch; extra == 'dev'
Requires-Dist: su6[all]; extra == 'dev'
Requires-Dist: types-bleach; extra == 'dev'
